gsl/__init__.py
gsl/antlr.py
gsl/dot_dict.py
gsl/g4v.py
gsl/strings.py
gsl/yaml.py
gsl/grammar/G4VVisitor.py
gsl/grammar/G4VisitorLexer.py
gsl/grammar/G4VisitorParser.py
gsl/grammar/G4VisitorVisitor.py
gsl/grammar/__init__.py
gsl-0.0.3.dist-info/DESCRIPTION.rst
gsl-0.0.3.dist-info/METADATA
gsl-0.0.3.dist-info/RECORD
gsl-0.0.3.dist-info/WHEEL
gsl-0.0.3.dist-info/entry_points.txt
gsl-0.0.3.dist-info/metadata.json
gsl-0.0.3.dist-info/top_level.txt
tests/grammar/ExprTestLexer.py
tests/grammar/ExprTestParser.py
tests/grammar/ExprTestVisitor.py
tests/grammar/HedgehogTestLexer.py
tests/grammar/HedgehogTestParser.py
tests/grammar/HedgehogTestVisitor.py
tests/grammar/SetTestLexer.py
tests/grammar/SetTestParser.py
tests/grammar/SetTestVisitor.py
tests/grammar/__init__.py
