Metadata-Version: 1.1
Name: gsl
Version: 0.0.3
Summary: General Scripting Library
Home-page: https://github.com/SillyFreak/gsl
Author: Silly Freak
Author-email: sillyfreak.ck@gmail.com
License: AGPLv3+
Keywords: code generation
Platform: UNKNOWN
Classifier: Development Status :: 4 - Beta
Classifier: Intended Audience :: Developers
Classifier: Topic :: Software Development
Classifier: License :: OSI Approved :: GNU Affero General Public License v3 or later (AGPLv3+)
Classifier: Programming Language :: Python :: 3.6
